{
	"id": "c63c7724-4314-4e3c-8fb8-5f1823de1672",
	"prevId": "00000000-0000-0000-0000-000000000000",
	"version": "7",
	"dialect": "postgresql",
	"tables": {
		"ops.operations": {
			"name": "operations",
			"schema": "ops",
			"columns": {
				"id": {
					"name": "id",
					"type": "text",
					"primaryKey": true,
					"notNull": true
				},
				"type": {
					"name": "type",
					"type": "text",
					"primaryKey": false,
					"notNull": true
				},
				"status": {
					"name": "status",
					"type": "text",
					"primaryKey": false,
					"notNull": true
				},
				"triggered_by": {
					"name": "triggered_by",
					"type": "text",
					"primaryKey": false,
					"notNull": true
				},
				"triggered_by_user": {
					"name": "triggered_by_user",
					"type": "text",
					"primaryKey": false,
					"notNull": false
				},
				"output": {
					"name": "output",
					"type": "text",
					"primaryKey": false,
					"notNull": false
				},
				"error_message": {
					"name": "error_message",
					"type": "text",
					"primaryKey": false,
					"notNull": false
				},
				"started_at": {
					"name": "started_at",
					"type": "timestamp with time zone",
					"primaryKey": false,
					"notNull": true,
					"default": "now()"
				},
				"completed_at": {
					"name": "completed_at",
					"type": "timestamp with time zone",
					"primaryKey": false,
					"notNull": false
				},
				"duration_ms": {
					"name": "duration_ms",
					"type": "integer",
					"primaryKey": false,
					"notNull": false
				}
			},
			"indexes": {},
			"foreignKeys": {},
			"compositePrimaryKeys": {},
			"uniqueConstraints": {},
			"policies": {},
			"checkConstraints": {},
			"isRLSEnabled": false
		}
	},
	"enums": {},
	"schemas": {
		"ops": "ops"
	},
	"sequences": {},
	"roles": {},
	"policies": {},
	"views": {},
	"_meta": {
		"columns": {},
		"schemas": {},
		"tables": {}
	}
}
